4bit_processor/control_unit.v
module control_unit(
    input [2:0] opcode,
    output reg alu_en
);

always @(*) begin
    case(opcode)
        3'b000: alu_en = 1; // ADD
        3'b001: alu_en = 1; // SUB
        3'b010: alu_en = 1; // AND
        3'b011: alu_en = 1; // OR
        3'b100: alu_en = 1; // XOR
        3'b101: alu_en = 1; // NOT
        default: alu_en = 0;
    endcase
end

endmodule

4bit_processor/memory.v
module memory(
    input [3:0] addr,
    output [7:0] data
);

reg [7:0] mem [0:15];

initial begin
    mem[0] = 8'b00000011;
    mem[1] = 8'b00000101;
    mem[2] = 8'b00001010;
    mem[3] = 8'b00001111;
end

assign data = mem[addr];

endmodule

4bit_processor/register_file.v
module register_file(
    input clk,
    input we,
    input [1:0] addr,
    input [3:0] data_in,
    output [3:0] data_out
);

reg [3:0] regfile [0:3];

always @(posedge clk)
begin
    if (we)
        regfile[addr] <= data_in;
end

assign data_out = regfile[addr];

endmodule

4bit_processor/alu.v
module alu(
    input [3:0] A,
    input [3:0] B,
    input [2:0] opcode,
    output reg [3:0] Y
);

always @(*) begin
    case(opcode)
        3'b000: Y = A + B;
        3'b001: Y = A - B;
        3'b010: Y = A & B;
        3'b011: Y = A | B;
        3'b100: Y = A ^ B;
        3'b101: Y = ~A;
        default: Y = 4'b0000;
    endcase
end

endmodule

4bit_processor/cpu_top.v
module cpu_top;

reg clk;
reg we;
reg [1:0] addr;
reg [3:0] data_in;
reg [3:0] A, B;
reg [2:0] opcode;

wire [3:0] Y;
wire [3:0] reg_data;
wire [7:0] mem_data;
wire alu_en;

// ALU
alu uut_alu (
    .A(A),
    .B(B),
    .opcode(opcode),
    .Y(Y)
);

// Register File
register_file uut_reg (
    .clk(clk),
    .we(we),
    .addr(addr),
    .data_in(data_in),
    .data_out(reg_data)
);

// Memory
memory uut_mem (
    .addr({2'b00, addr}),
    .data(mem_data)
);

// Control Unit
control_unit uut_ctrl (
    .opcode(opcode),
    .alu_en(alu_en)
);

initial begin
    $dumpfile("cpu_wave.vcd");
    $dumpvars(0, cpu_top);

    clk = 0;
    we = 1;

    // Write values into registers
    addr = 2'b00; data_in = 4'b0101; #10;
    addr = 2'b01; data_in = 4'b0011; #10;

    // ALU inputs
    A = 4'b0101;
    B = 4'b0011;

    opcode = 3'b000; #10; // ADD
    opcode = 3'b001; #10; // SUB
    opcode = 3'b010; #10; // AND
    opcode = 3'b011; #10; // OR
    opcode = 3'b100; #10; // XOR
    opcode = 3'b101; #10; // NOT

    $finish;
end

always #5 clk = ~clk;

endmodule

4bit_processor/cpu_wave.vcd
$date
	Wed Jun 24 17:29:25 2026
$end
$version
	Icarus Verilog
$end
$timescale
	1s
$end
$scope module cpu_top $end
$var wire 4 ! reg_data [3:0] $end
$var wire 8 " mem_data [7:0] $end
$var wire 1 # alu_en $end
$var wire 4 $ Y [3:0] $end
$var reg 4 % A [3:0] $end
$var reg 4 & B [3:0] $end
$var reg 2 ' addr [1:0] $end
$var reg 1 ( clk $end
$var reg 4 ) data_in [3:0] $end
$var reg 3 * opcode [2:0] $end
$var reg 1 + we $end
$scope module uut_alu $end
$var wire 4 , A [3:0] $end
$var wire 4 - B [3:0] $end
$var wire 3 . opcode [2:0] $end
$var reg 4 / Y [3:0] $end
$upscope $end
$scope module uut_ctrl $end
$var wire 3 0 opcode [2:0] $end
$var reg 1 # alu_en $end
$upscope $end
$scope module uut_mem $end
$var wire 4 1 addr [3:0] $end
$var wire 8 2 data [7:0] $end
$upscope $end
$scope module uut_reg $end
$var wire 2 3 addr [1:0] $end
$var wire 1 ( clk $end
$var wire 4 4 data_in [3:0] $end
$var wire 4 5 data_out [3:0] $end
$var wire 1 + we $end
$upscope $end
$upscope $end
$enddefinitions $end
$comment Show the parameter values. $end
$dumpall
$end
#0
$dumpvars
bx 5
b101 4
b0 3
b11 2
b0 1
bx 0
bx /
bx .
bx -
bx ,
1+
bx *
b101 )
0(
b0 '
bx &
bx %
bx $
x#
b11 "
bx !
$end
#5
b101 !
b101 5
1(
#10
b101 "
b101 2
b1 1
bx !
bx 5
0(
b11 )
b11 4
b1 '
b1 3
#15
b11 !
b11 5
1(
#20
1#
b1000 $
b1000 /
0(
b0 *
b0 .
b0 0
b11 &
b11 -
b101 %
b101 ,
#25
1(
#30
b10 $
b10 /
0(
b1 *
b1 .
b1 0
#35
1(
#40
b1 $
b1 /
0(
b10 *
b10 .
b10 0
#45
1(
#50
b111 $
b111 /
0(
b11 *
b11 .
b11 0
#55
1(
#60
b110 $
b110 /
0(
b100 *
b100 .
b100 0
#65
1(
#70
b1010 $
b1010 /
0(
b101 *
b101 .
b101 0
